MANIFEST.in
setup.py
django_template_test.egg-info/PKG-INFO
django_template_test.egg-info/SOURCES.txt
django_template_test.egg-info/dependency_links.txt
django_template_test.egg-info/not-zip-safe
django_template_test.egg-info/top_level.txt
template_test/__init__.py
template_test/templates/404.html
template_test/templates/500.html
template_test/templates/base-fluid.html
template_test/templates/base-sidebar.html
template_test/templates/base-small.html
template_test/templates/base.html
template_test/templates/template.html