Metadata-Version: 1.0
Name: django-template-test
Version: 0.1.1
Summary: A basic django template used for testing.
Home-page: http://github.com/adieu/django-template-test
Author: Ivan Diao
Author-email: adieu@adieu.me
License: BSD
Platform: UNKNOWN
Classifier: Framework :: Django
Classifier: Intended Audience :: Developers
Classifier: Intended Audience :: System Administrators
Classifier: Operating System :: OS Independent
Classifier: Topic :: Software Development
